causalnex/__init__.py
causalnex/contrib/__init__.py
causalnex/discretiser/__init__.py
causalnex/discretiser/abstract_discretiser.py
causalnex/discretiser/discretiser.py
causalnex/discretiser/discretiser_strategy.py
causalnex/ebaybbn/__init__.py
causalnex/ebaybbn/bbn.py
causalnex/ebaybbn/exceptions.py
causalnex/ebaybbn/graph.py
causalnex/ebaybbn/utils.py
causalnex/estimator/__init__.py
causalnex/estimator/em.py
causalnex/evaluation/__init__.py
causalnex/evaluation/evaluation.py
causalnex/inference/__init__.py
causalnex/inference/inference.py
causalnex/network/__init__.py
causalnex/network/network.py
causalnex/network/sklearn/__init__.py
causalnex/network/sklearn/models.py
causalnex/plots/__init__.py
causalnex/plots/display.py
causalnex/plots/plots.py
causalnex/structure/__init__.py
causalnex/structure/categorical_variable_mapper.py
causalnex/structure/dynotears.py
causalnex/structure/notears.py
causalnex/structure/structuremodel.py
causalnex/structure/transformers.py
causalnex/structure/data_generators/__init__.py
causalnex/structure/data_generators/core.py
causalnex/structure/data_generators/wrappers.py
causalnex/structure/pytorch/__init__.py
causalnex/structure/pytorch/core.py
causalnex/structure/pytorch/nonlinear.py
causalnex/structure/pytorch/notears.py
causalnex/structure/pytorch/dist_type/__init__.py
causalnex/structure/pytorch/dist_type/_base.py
causalnex/structure/pytorch/dist_type/binary.py
causalnex/structure/pytorch/dist_type/categorical.py
causalnex/structure/pytorch/dist_type/continuous.py
causalnex/structure/pytorch/dist_type/ordinal.py
causalnex/structure/pytorch/dist_type/poisson.py
causalnex/structure/pytorch/sklearn/__init__.py
causalnex/structure/pytorch/sklearn/_base.py
causalnex/structure/pytorch/sklearn/clf.py
causalnex/structure/pytorch/sklearn/reg.py
causalnex/utils/__init__.py
causalnex/utils/data_utils.py
causalnex/utils/decision_tree_tools.py
causalnex/utils/pgmpy_utils.py
causalnex-0.12.1.dist-info/LICENSE.md
causalnex-0.12.1.dist-info/METADATA
causalnex-0.12.1.dist-info/WHEEL
causalnex-0.12.1.dist-info/top_level.txt
causalnex-0.12.1.dist-info/RECORD
