Metadata-Version: 2.1
Name: causalnex
Version: 0.12.1
Summary: Toolkit for causal reasoning (Bayesian Networks / Inference)
Home-page: https://github.com/quantumblacklabs/causalnex
Author: QuantumBlack Labs
Author-email: causalnex@quantumblack.com
License: Apache Software License (Apache 2.0)
Keywords: Causal Reasoning,Bayesian Network,Inference,Structure Learning,Do-Calculus
Classifier: Development Status :: 4 - Beta
Classifier: Programming Language :: Python :: 3.8
Classifier: Programming Language :: Python :: 3.9
Classifier: Programming Language :: Python :: 3.10
Requires-Python: >=3.8, <3.11
License-File: LICENSE.md
Requires-Dist: ipython (>=8.10.0)
Requires-Dist: networkx (>=2.5)
Requires-Dist: numpy (<1.24,>=1.14.2)
Requires-Dist: pandas (<2.0,>=1.0)
Requires-Dist: pathos (>=0.2.7)
Requires-Dist: pgmpy (<0.1.20,>=0.1.14)
Requires-Dist: pyvis (>=0.3.2)
Requires-Dist: scipy (>=1.7)
Requires-Dist: setuptools (>=65.5.1)
Requires-Dist: torch (>=1.7)
Requires-Dist: wheel (>=0.38.0)
Requires-Dist: scikit-learn (!=0.22.2.post1,!=0.24.1,>=0.22.0) ; python_version < "3.9"
Requires-Dist: scikit-learn (>=0.25.0) ; python_version == "3.10"
Requires-Dist: scikit-learn (!=0.24.1,>=0.24.0) ; python_version == "3.9"
Provides-Extra: all
Requires-Dist: mdlp-discretization (~=0.3.3) ; extra == 'all'
Provides-Extra: discretiser
Requires-Dist: mdlp-discretization (~=0.3.3) ; extra == 'discretiser'
